django_rstblog-0.1.2.dist-info/METADATA
django_rstblog-0.1.2.dist-info/RECORD
django_rstblog-0.1.2.dist-info/WHEEL
django_rstblog-0.1.2.dist-info/top_level.txt
rstblog/__init__.py
rstblog/admin.py
rstblog/apps.py
rstblog/const.py
rstblog/forms.py
rstblog/models.py
rstblog/tests.py
rstblog/urls.py
rstblog/version.py
rstblog/views.py
rstblog/migrations/0001_initial.py
rstblog/migrations/__init__.py
rstblog/static/css/alabaster.css
rstblog/static/css/base.css
rstblog/static/css/basic.css
rstblog/static/css/pygments.css
rstblog/static/css/pygments.css.colorful
rstblog/static/css/pygments.css.monokai
rstblog/static/css/pygments.css.sphinx
rstblog/static/js/bootstrap.min.js
rstblog/static/js/jquery-3.1.0.js
rstblog/static/js/jquery-migrate-1.4.1.js
rstblog/static/js/jquery.align-column.js
rstblog/static/js/jquery.min.js
rstblog/templates/article_box.html
rstblog/templates/article_evidence.html
rstblog/templates/blog_home.html
rstblog/templates/index.html
rstblog/templates/load_article.html
rstblog/templates/show.html
rstblog/templates/show_stats.html
rstblog/templatetags/__init__.py
rstblog/templatetags/rstblog_extras.py
