Metadata-Version: 2.1
Name: django-rstblog
Version: 0.1.2
Summary: A Django app to manage a blog driven by articles written using a markup language
Home-page: https://github.com/l-dfa/django-rstblog
Author: luciano de falco alfano
Author-email: ldefalcoalfano@hotmail.com
License: MIT License
Platform: UNKNOWN
Classifier: Development Status :: 4 - Beta
Classifier: Environment :: Web Environment
Classifier: Framework :: Django
Classifier: Framework :: Django :: 2.0
Classifier: Intended Audience :: Developers
Classifier: License :: OSI Approved :: MIT License
Classifier: Operating System :: OS Independent
Classifier: Programming Language :: Python
Classifier: Programming Language :: Python :: 3.6
Classifier: Topic :: Internet :: WWW/HTTP
Classifier: Topic :: Internet :: WWW/HTTP :: Dynamic Content
Requires-Dist: docutils (==0.14)
Requires-Dist: Django (==2.1.2)
Requires-Dist: django-concurrency (==1.4)
Requires-Dist: Markdown (==2.6.11)
Requires-Dist: Pygments (==2.2.0)
Requires-Dist: python-markdown-math (==0.6)
